pybuilder_setup_cfg/__init__.py
pybuilder_setup_cfg-0.0.18.dist-info/METADATA
pybuilder_setup_cfg-0.0.18.dist-info/WHEEL
pybuilder_setup_cfg-0.0.18.dist-info/namespace_packages.txt
pybuilder_setup_cfg-0.0.18.dist-info/top_level.txt
pybuilder_setup_cfg-0.0.18.dist-info/zip-safe
pybuilder_setup_cfg-0.0.18.dist-info/RECORD
