Metadata-Version: 2.1
Name: pybuilder-setup-cfg
Version: 0.0.18
Summary: PyBuilder plugin for getting information from setup.cfg file or environment variables
Home-page: https://github.com/margru/pybuilder-setup-cfg
Author: Martin Gruber
Author-email: martin.gruber@email.cz
License: MIT
Platform: UNKNOWN
Classifier: Development Status :: 3 - Alpha
Classifier: License :: OSI Approved :: MIT License
Classifier: Programming Language :: Python :: 2.7
Requires-Dist: configparser
